pgwrapper/__init__.py
pgwrapper/pgpool.py
pgwrapper/pgwrap.py
pgwrapper-0.3.5.dist-info/LICENSE
pgwrapper-0.3.5.dist-info/METADATA
pgwrapper-0.3.5.dist-info/WHEEL
pgwrapper-0.3.5.dist-info/top_level.txt
pgwrapper-0.3.5.dist-info/RECORD
