Metadata-Version: 2.1
Name: pgwrapper
Version: 0.3.5
Summary: A simple, fast way to access postgresql
Home-page: https://github.com/LaoLiulaoliu/pgwrapper
Author: Richard Liu
Author-email: miraclecome@gmail.com
Classifier: Programming Language :: Python :: 3.10
Classifier: Development Status :: 4 - Beta
Classifier: Environment :: Other Environment
Classifier: Intended Audience :: Developers
Classifier: License :: OSI Approved :: GNU General Public License v3 (GPLv3)
Classifier: Operating System :: OS Independent
Classifier: Topic :: Software Development :: Libraries :: Python Modules
License-File: LICENSE
Requires-Dist: psycopg2 (>=2.9.6)
